dnspooh/__init__.py
dnspooh/__main__.py
dnspooh/cli.py
dnspooh/config.py
dnspooh/exceptions.py
dnspooh/geoip
dnspooh/helpers.py
dnspooh/https.py
dnspooh/pool.py
dnspooh/proxy.py
dnspooh/server.py
dnspooh/timers.py
dnspooh/upstream.py
dnspooh/version.py
dnspooh/middlewares/__init__.py
dnspooh/middlewares/block.py
dnspooh/middlewares/cache.py
dnspooh/middlewares/hosts.py
dnspooh/middlewares/log.py
dnspooh/middlewares/rules.py
tests/__init__.py
tests/block.py
tests/rules.py
tests/trigger_error.py
dnspooh-1.3.3.dist-info/LICENSE
dnspooh-1.3.3.dist-info/METADATA
dnspooh-1.3.3.dist-info/WHEEL
dnspooh-1.3.3.dist-info/entry_points.txt
dnspooh-1.3.3.dist-info/top_level.txt
dnspooh-1.3.3.dist-info/RECORD
