Metadata-Version: 2.1
Name: dnspooh
Version: 1.3.3
Summary: A Lightweight DNS MitM Proxy
Home-page: https://github.com/tabris17/dnspooh
Author: tabris17
Author-email: tabris17 <tabris17.cn@gmail.com>
License: MIT License
Project-URL: Homepage, https://github.com/tabris17/dnspooh
Project-URL: Bug Tracker, https://github.com/tabris17/dnspooh/issues
Classifier: Topic :: Internet :: Name Service (DNS)
Classifier: Programming Language :: Python :: 3
Classifier: Programming Language :: Python :: 3.10
Classifier: Programming Language :: Python :: 3.11
Classifier: Programming Language :: Python :: 3.12
Classifier: Programming Language :: Python :: 3 :: Only
Classifier: License :: OSI Approved :: MIT License
Classifier: Operating System :: OS Independent
Requires-Python: >=3.10
License-File: LICENSE
Requires-Dist: cachetools ==5.2.0
Requires-Dist: certifi ==2022.12.7
Requires-Dist: dnslib ==0.9.23
Requires-Dist: maxminddb ==2.2.0
Requires-Dist: pyparsing ==3.0.9
Requires-Dist: PyYAML ==6.0.1
